claffinity/__init__.py
claffinity/competition_label_affinity.py
claffinity/high_accuracy_binding_equations.py
claffinity-1.0.2.dist-info/LICENSE
claffinity-1.0.2.dist-info/METADATA
claffinity-1.0.2.dist-info/WHEEL
claffinity-1.0.2.dist-info/top_level.txt
claffinity-1.0.2.dist-info/RECORD
