Metadata-Version: 2.1
Name: claffinity
Version: 1.0.2
Summary: A tool for investigating the impact of labelled ligand affinity in competition experiments.
License: MIT License
Keywords: competition,label,ligand
Platform: UNKNOWN
Classifier: License :: OSI Approved :: MIT License
Classifier: Programming Language :: Python :: 3.7
License-File: LICENSE
Requires-Dist: matplotlib
Requires-Dist: numpy (>=1.15)
Requires-Dist: pandas (>=1.2.2)
Requires-Dist: mpmath (>=1.1.0)
Requires-Dist: progressbar2
